hyrule/__init__.py
hyrule/anaphoric.hy
hyrule/argmove.hy
hyrule/collections.hy
hyrule/control.hy
hyrule/destructure.hy
hyrule/hy_init.hy
hyrule/hypprint.hy
hyrule/iterables.hy
hyrule/macrotools.hy
hyrule/misc.hy
hyrule/sequences.hy
hyrule-0.1.dist-info/AUTHORS
hyrule-0.1.dist-info/LICENSE
hyrule-0.1.dist-info/METADATA
hyrule-0.1.dist-info/WHEEL
hyrule-0.1.dist-info/top_level.txt
hyrule-0.1.dist-info/RECORD
