Metadata-Version: 2.1
Name: hyrule
Version: 0.1
Summary: A utility library for the Hy programming language
Home-page: UNKNOWN
Author: Paul Tagliamonte
Author-email: tag@pault.ag
License: Expat
Project-URL: Documentation, https://hyrule.readthedocs.io
Project-URL: Source, https://github.com/hylang/hyrule
Platform: any
Classifier: Development Status :: 4 - Beta
Classifier: License :: DFSG approved
Classifier: License :: OSI Approved :: MIT License
Classifier: Operating System :: OS Independent
Classifier: Programming Language :: Lisp
Classifier: Programming Language :: Python
Classifier: Programming Language :: Python :: 3
Classifier: Programming Language :: Python :: 3.7
Classifier: Programming Language :: Python :: 3.8
Classifier: Programming Language :: Python :: 3.9
Classifier: Programming Language :: Python :: 3.10
License-File: LICENSE
License-File: AUTHORS
Requires-Dist: hy (==1.0a4)
